pegasus_cli/__init__.py
pegasus_cli/__main__.py
pegasus_cli/cli.py
pegasus_cli/generate.py
pegasus_cli/jinja.py
pegasus_cli/monkeypatch.py
pegasus_cli/ruff.py
pegasus_cli/startapp.py
pegasus_cli/templates/app_template/hooks/post_gen_project.py
pegasus_cli/templates/app_template/{{cookiecutter.app_name}}/__init__.py
pegasus_cli/templates/app_template/{{cookiecutter.app_name}}/admin.py
pegasus_cli/templates/app_template/{{cookiecutter.app_name}}/apps.py
pegasus_cli/templates/app_template/{{cookiecutter.app_name}}/forms.py
pegasus_cli/templates/app_template/{{cookiecutter.app_name}}/models.py
pegasus_cli/templates/app_template/{{cookiecutter.app_name}}/urls.py
pegasus_cli/templates/app_template/{{cookiecutter.app_name}}/views.py
pegasus_cli/templates/app_template/{{cookiecutter.app_name}}/migrations/__init__.py
pegasus_cli/templates/app_template/{{cookiecutter.app_name}}/tests/__init__.py
pegasus_cli/templates/app_template_templates/{{cookiecutter.template_dir_name}}/{{app_name}}_home.html
pegasus_cli/templates/internal/cli_output.txt
pegasus_cli/templates/model_templates/{{cookiecutter.template_dir_name}}/{{model_name_lower}}_detail.html
pegasus_cli/templates/model_templates/{{cookiecutter.template_dir_name}}/{{model_name_lower}}_form.html
pegasus_cli/templates/model_templates/{{cookiecutter.template_dir_name}}/{{model_name_lower}}_list.html
pegasus_cli-0.11.dist-info/licenses/LICENSE
tests/test_cli.py
tests/test_generate.py
pegasus_cli-0.11.dist-info/METADATA
pegasus_cli-0.11.dist-info/WHEEL
pegasus_cli-0.11.dist-info/entry_points.txt
pegasus_cli-0.11.dist-info/top_level.txt
pegasus_cli-0.11.dist-info/RECORD
