Metadata-Version: 2.4
Name: pegasus-cli
Version: 0.11
Summary: CLI for Django and SaaS Pegasus
Author: czue, snopoke
License: Apache-2.0
Project-URL: Homepage, https://github.com/saaspegasus/pegasus-cli
Project-URL: Changelog, https://github.com/saaspegasus/pegasus-cli/releases
Project-URL: Issues, https://github.com/saaspegasus/pegasus-cli/issues
Project-URL: CI, https://github.com/saaspegasus/pegasus-cli/actions
Classifier: License :: OSI Approved :: Apache Software License
Requires-Python: >=3.9
License-File: LICENSE
Requires-Dist: click
Requires-Dist: cookiecutter
Provides-Extra: dev
Requires-Dist: pytest; extra == "dev"
Requires-Dist: ruff; extra == "dev"
Requires-Dist: pre-commit; extra == "dev"
Dynamic: license-file
